<?xml version="1.0" encoding="utf-8"?>
<BOM>
    <BO>
        <AdmInfo>
            <Object>22</Object>
            <Version>2</Version>
        </AdmInfo>
        <Documents>
            <row>
                <DocEntry>6354</DocEntry>
                <DocNum>6302</DocNum>
                <DocType>dDocument_Items</DocType>
                <HandWritten>tNO</HandWritten>
                <Printed>psNo</Printed>
                <DocDate>20230331</DocDate>
                <DocDueDate>2023-03-31</DocDueDate>
                <CardCode>P0009</CardCode>
                <CardName>GONZALEZ RIVAS LUIS EDUARDO</CardName>
                <DocTotal>16903.114000</DocTotal>
                <DocCurrency>USD</DocCurrency>
                <DocRate>22.700000</DocRate>
                <Reference1>6302</Reference1>
                <Comments>X</Comments>
                <JournalMemo>Pedidos - P0009</JournalMemo>
                <PaymentGroupCode>1</PaymentGroupCode>
                <DocTime>0228</DocTime>
                <SalesPersonCode>-1</SalesPersonCode>
                <TransportationCode>-1</TransportationCode>
                <Confirmed>tYES</Confirmed>
                <SummeryType>dNoSummary</SummeryType>
                <ContactPersonCode>0</ContactPersonCode>
                <ShowSCN>tNO</ShowSCN>
                <Series>15</Series>
                <TaxDate>20230331</TaxDate>
                <DocObjectCode>22</DocObjectCode>
                <FederalTaxID>GORL740914623</FederalTaxID>
                <DiscountPercent>0.000000</DiscountPercent>
                <DocTotalFc>744.631000</DocTotalFc>
                <RevisionPo>tYES</RevisionPo>
                <BlockDunning>tNO</BlockDunning>
                <Pick>tNO</Pick>
                <PaymentMethod />
                <PaymentBlock>tNO</PaymentBlock>
                <MaximumCashDiscount>tNO</MaximumCashDiscount>
                <WareHouseUpdateType>dwh_OrdersFromVendors</WareHouseUpdateType>
                <Rounding>tNO</Rounding>
                <DeferredTax>tYES</DeferredTax>
                <NumberOfInstallments>1</NumberOfInstallments>
                <ApplyTaxOnFirstInstallment>tNO</ApplyTaxOnFirstInstallment>
                <DocumentSubType>bod_None</DocumentSubType>
                <Address2>SAN FCO DE SALES No. 76 COLONIA LA PUNTA

                    TONALA, JALISCO,45425, CDM
                    MX</Address2>
                <UseShpdGoodsAct>tNO</UseShpdGoodsAct>
                <IsPayToBank>tNO</IsPayToBank>
                <DownPayment>0.000000</DownPayment>
                <ReserveInvoice>tNO</ReserveInvoice>
                <LanguageCode>25</LanguageCode>
                <SequenceModel>0</SequenceModel>
                <UseCorrectionVATGroup>tNO</UseCorrectionVATGroup>
                <DownPaymentAmount>0.000000</DownPaymentAmount>
                <DownPaymentPercentage>0.000000</DownPaymentPercentage>
                <DownPaymentType>dptInvoice</DownPaymentType>
                <DownPaymentAmountSC>0.000000</DownPaymentAmountSC>
                <DownPaymentAmountFC>0.000000</DownPaymentAmountFC>
                <VatPercent>0.000000</VatPercent>
                <RoundingDiffAmount>0.000000</RoundingDiffAmount>
                <ControlAccount>_SYS00000000058</ControlAccount>
                <InsuranceOperation347>tNO</InsuranceOperation347>
                <ArchiveNonremovableSalesQuotation>tNO</ArchiveNonremovableSalesQuotation>
                <ExtraMonth>0</ExtraMonth>
                <ExtraDays>30</ExtraDays>
                <CashDiscountDateOffset>0</CashDiscountDateOffset>
                <StartFrom>pdt_None</StartFrom>
                <NTSApproved>tNO</NTSApproved>
                <EDocGenerationType>edocNotRelevant</EDocGenerationType>
                <EDocStatus>edoc_Ok</EDocStatus>
                <DownPaymentStatus>so_Open</DownPaymentStatus>
                <GroupHandWritten>tNO</GroupHandWritten>
                <CreateOnlineQuotation>tNO</CreateOnlineQuotation>
                <ApplyCurrentVATRatesForDownPaymentsToDraw>tNO</ApplyCurrentVATRatesForDownPaymentsToDraw>
                <ClosingOption>coByCurrentSystemDate</ClosingOption>
                <OpenForLandedCosts>tYES</OpenForLandedCosts>
                <RelevantToGTS>tNO</RelevantToGTS>
                <IsAlteration>tNO</IsAlteration>
                <DocumentDelivery>ddtNoneSeleted</DocumentDelivery>
                <ReuseDocumentNum>tNO</ReuseDocumentNum>
                <ReuseNotaFiscalNum>tNO</ReuseNotaFiscalNum>
                <PrintSEPADirect>tNO</PrintSEPADirect>
                <InterimType>boidt_None</InterimType>
                <RelatedType>-1</RelatedType>
                <ExcludeFromTaxReportControlStatementVAT>tNO</ExcludeFromTaxReportControlStatementVAT>
                <CommissionTrade>ct_Empty</CommissionTrade>
                <CommissionTradeReturn>tNO</CommissionTradeReturn>
                <UseBillToAddrToDetermineTax>tNO</UseBillToAddrToDetermineTax>
                <U_B1SYS_MainUsage />
                <U_Prioridad>1</U_Prioridad>
                <U_Procesado>N</U_Procesado>
                <U_MetodoDePago>PPD</U_MetodoDePago>
                <U_Especial>L</U_Especial>
                <U_SIZ_CreadoPor>4</U_SIZ_CreadoPor>
            </row>
        </Documents>
        <Document_Lines>
            <row>
                <LineNum>0</LineNum>
                <ItemCode>10083</ItemCode>
                <ItemDescription>TRIPLAY CAOBILLA 3 MM. DE ESPESOR 4X8.</ItemDescription>
                <Quantity>50.000000</Quantity>
                <ShipDate>20230412</ShipDate>
                <Price>215.500000</Price>
                <PriceAfterVAT>249.980000</PriceAfterVAT>
                <Currency>MXP</Currency>
                <Rate>0.000000</Rate>
                <DiscountPercent>0.000000</DiscountPercent>
                <VendorNum />
                <WarehouseCode>AMP-CC</WarehouseCode>
                <SalesPersonCode>-1</SalesPersonCode>
                <CommisionPercent>0.000000</CommisionPercent>
                <TreeType>iNotATree</TreeType>
                <AccountCode>_SYS00000000022</AccountCode>
                <UseBaseUnits>tNO</UseBaseUnits>
                <SupplierCatNum />
                <ProjectCode />
                <VatGroup>W3</VatGroup>
                <Height1>0.000000</Height1>
                <Height2>0.000000</Height2>
                <Lengh1>0.000000</Lengh1>
                <Lengh2>0.000000</Lengh2>
                <Weight1>0.000000</Weight1>
                <Weight2>0.000000</Weight2>
                <Factor1>1.000000</Factor1>
                <Factor2>1.000000</Factor2>
                <Factor3>1.000000</Factor3>
                <Factor4>1.000000</Factor4>
                <BaseType>-1</BaseType>
                <Volume>0.000000</Volume>
                <VolumeUnit>4</VolumeUnit>
                <Width1>0.000000</Width1>
                <Width2>0.000000</Width2>
                <Address />
                <TaxCode>W3</TaxCode>
                <TaxType>tt_Yes</TaxType>
                <TaxLiable>tYES</TaxLiable>
                <FreeText />
                <ShippingMethod>-1</ShippingMethod>
                <CorrectionInvoiceItem>ciis_ShouldBe</CorrectionInvoiceItem>
                <CorrInvAmountToStock>0.000000</CorrInvAmountToStock>
                <CorrInvAmountToDiffAcct>0.000000</CorrInvAmountToDiffAcct>
                <WTLiable>tNO</WTLiable>
                <DeferredTax>tYES</DeferredTax>
                <MeasureUnit>PZA</MeasureUnit>
                <UnitsOfMeasurment>1.000000</UnitsOfMeasurment>
                <LineTotal>10775.000000</LineTotal>
                <TaxPercentagePerRow>16.000000</TaxPercentagePerRow>
                <TaxTotal>1724.000000</TaxTotal>
                <ConsumerSalesForecast>tNO</ConsumerSalesForecast>
                <ExciseAmount>0.000000</ExciseAmount>
                <SWW />
                <DistributeExpense>tYES</DistributeExpense>
                <RowTotalFC>474.670000</RowTotalFC>
                <TaxOnly>tNO</TaxOnly>
                <UnitPrice>215.500000</UnitPrice>
                <LineStatus>bost_Open</LineStatus>
                <PackageQuantity>50.000000</PackageQuantity>
                <LineType>dlt_Regular</LineType>
                <ChangeAssemlyBoMWarehouse>N</ChangeAssemlyBoMWarehouse>
                <GrossBuyPrice>0.000000</GrossBuyPrice>
                <GrossProfitTotalBasePrice>0.000000</GrossProfitTotalBasePrice>
                <RequiredQuantity>0.000000</RequiredQuantity>
                <WithoutInventoryMovement>tNO</WithoutInventoryMovement>
                <DocEntry>6354</DocEntry>
                <Surpluses>0.000000</Surpluses>
                <DefectAndBreakup>0.000000</DefectAndBreakup>
                <Shortages>0.000000</Shortages>
                <ConsiderQuantity>tNO</ConsiderQuantity>
                <PartialRetirement>tNO</PartialRetirement>
                <RetirementQuantity>0.000000</RetirementQuantity>
                <RetirementAPC>0.000000</RetirementAPC>
                <ThirdParty>tNO</ThirdParty>
                <GrossProfit>0.000000</GrossProfit>
                <GrossProfitFC>0.000000</GrossProfitFC>
                <GrossProfitSC>0.000000</GrossProfitSC>
                <UoMEntry>-1</UoMEntry>
                <InventoryQuantity>50.000000</InventoryQuantity>
                <Incoterms>0</Incoterms>
                <TransportMode>0</TransportMode>
                <ChangeInventoryQuantityIndependently>tNO</ChangeInventoryQuantityIndependently>
                <FreeOfChargeBP>tNO</FreeOfChargeBP>
                <GrossPrice>249.980000</GrossPrice>
                <GrossTotal>12499.000000</GrossTotal>
                <GrossTotalFC>550.617000</GrossTotalFC>
                <NCMCode>-1</NCMCode>
                <U_Procesado>0</U_Procesado>
            </row>
            <row>
                <LineNum>1</LineNum>
                <ItemCode>10083</ItemCode>
                <ItemDescription>TRIPLAY CAOBILLA 3 MM. DE ESPESOR 4X8.</ItemDescription>
                <Quantity>10.000000</Quantity>
                <ShipDate>20230429</ShipDate>
                <Price>215.500000</Price>
                <PriceAfterVAT>249.980000</PriceAfterVAT>
                <Currency>MXP</Currency>
                <Rate>0.000000</Rate>
                <DiscountPercent>0.000000</DiscountPercent>
                <VendorNum />
                <WarehouseCode>AMP-CC</WarehouseCode>
                <SalesPersonCode>-1</SalesPersonCode>
                <CommisionPercent>0.000000</CommisionPercent>
                <TreeType>iNotATree</TreeType>
                <AccountCode>_SYS00000000022</AccountCode>
                <UseBaseUnits>tNO</UseBaseUnits>
                <SupplierCatNum />
                <ProjectCode />
                <VatGroup>W3</VatGroup>
                <Height1>0.000000</Height1>
                <Height2>0.000000</Height2>
                <Lengh1>0.000000</Lengh1>
                <Lengh2>0.000000</Lengh2>
                <Weight1>0.000000</Weight1>
                <Weight2>0.000000</Weight2>
                <Factor1>1.000000</Factor1>
                <Factor2>1.000000</Factor2>
                <Factor3>1.000000</Factor3>
                <Factor4>1.000000</Factor4>
                <BaseType>-1</BaseType>
                <Volume>0.000000</Volume>
                <VolumeUnit>4</VolumeUnit>
                <Width1>0.000000</Width1>
                <Width2>0.000000</Width2>
                <Address />
                <TaxCode>W3</TaxCode>
                <TaxType>tt_Yes</TaxType>
                <TaxLiable>tYES</TaxLiable>
                <FreeText />
                <ShippingMethod>-1</ShippingMethod>
                <CorrectionInvoiceItem>ciis_ShouldBe</CorrectionInvoiceItem>
                <CorrInvAmountToStock>0.000000</CorrInvAmountToStock>
                <CorrInvAmountToDiffAcct>0.000000</CorrInvAmountToDiffAcct>
                <WTLiable>tNO</WTLiable>
                <DeferredTax>tYES</DeferredTax>
                <MeasureUnit>PZA</MeasureUnit>
                <UnitsOfMeasurment>1.000000</UnitsOfMeasurment>
                <LineTotal>2155.000000</LineTotal>
                <TaxPercentagePerRow>16.000000</TaxPercentagePerRow>
                <TaxTotal>344.800000</TaxTotal>
                <ConsumerSalesForecast>tNO</ConsumerSalesForecast>
                <ExciseAmount>0.000000</ExciseAmount>
                <SWW />
                <DistributeExpense>tYES</DistributeExpense>
                <RowTotalFC>94.934000</RowTotalFC>
                <TaxOnly>tNO</TaxOnly>
                <UnitPrice>215.500000</UnitPrice>
                <LineStatus>bost_Open</LineStatus>
                <PackageQuantity>10.000000</PackageQuantity>
                <LineType>dlt_Regular</LineType>
                <ChangeAssemlyBoMWarehouse>N</ChangeAssemlyBoMWarehouse>
                <GrossBuyPrice>0.000000</GrossBuyPrice>
                <GrossProfitTotalBasePrice>0.000000</GrossProfitTotalBasePrice>
                <WithoutInventoryMovement>tNO</WithoutInventoryMovement>
                <DocEntry>6354</DocEntry>
                <ConsiderQuantity>tNO</ConsiderQuantity>
                <PartialRetirement>tNO</PartialRetirement>
                <RetirementAPC>0.000000</RetirementAPC>
                <ThirdParty>tNO</ThirdParty>
                <GrossProfit>0.000000</GrossProfit>
                <GrossProfitFC>0.000000</GrossProfitFC>
                <GrossProfitSC>0.000000</GrossProfitSC>
                <UoMEntry>-1</UoMEntry>
                <InventoryQuantity>10.000000</InventoryQuantity>
                <ChangeInventoryQuantityIndependently>tNO</ChangeInventoryQuantityIndependently>
                <FreeOfChargeBP>tNO</FreeOfChargeBP>
                <GrossPrice>249.980000</GrossPrice>
                <GrossTotal>2499.800000</GrossTotal>
                <GrossTotalFC>110.123000</GrossTotalFC>
                <NCMCode>-1</NCMCode>
                <U_Procesado>0</U_Procesado>
            </row>
            <row>
                <LineNum>2</LineNum>
                <ItemCode>10084</ItemCode>
                <ItemDescription>TRIPLAY DE PINO 6 MM. DE ESPESOR 4X8.</ItemDescription>
                <Quantity>5.000000</Quantity>
                <ShipDate>20230331</ShipDate>
                <Price>328.330000</Price>
                <PriceAfterVAT>380.862800</PriceAfterVAT>
                <Currency>MXP</Currency>
                <Rate>0.000000</Rate>
                <DiscountPercent>0.000000</DiscountPercent>
                <VendorNum />
                <WarehouseCode>AMP-CC</WarehouseCode>
                <SalesPersonCode>-1</SalesPersonCode>
                <CommisionPercent>0.000000</CommisionPercent>
                <TreeType>iNotATree</TreeType>
                <AccountCode>_SYS00000000022</AccountCode>
                <UseBaseUnits>tNO</UseBaseUnits>
                <SupplierCatNum />
                <ProjectCode />
                <VatGroup>W3</VatGroup>
                <Height1>0.000000</Height1>
                <Height2>0.000000</Height2>
                <Lengh1>0.000000</Lengh1>
                <Lengh2>0.000000</Lengh2>
                <Weight1>0.000000</Weight1>
                <Weight2>0.000000</Weight2>
                <Factor1>1.000000</Factor1>
                <Factor2>1.000000</Factor2>
                <Factor3>1.000000</Factor3>
                <Factor4>1.000000</Factor4>
                <BaseType>-1</BaseType>
                <Volume>0.000000</Volume>
                <VolumeUnit>4</VolumeUnit>
                <Width1>0.000000</Width1>
                <Width2>0.000000</Width2>
                <Address />
                <TaxCode>W3</TaxCode>
                <TaxType>tt_Yes</TaxType>
                <TaxLiable>tYES</TaxLiable>
                <FreeText />
                <ShippingMethod>-1</ShippingMethod>
                <CorrectionInvoiceItem>ciis_ShouldBe</CorrectionInvoiceItem>
                <CorrInvAmountToStock>0.000000</CorrInvAmountToStock>
                <CorrInvAmountToDiffAcct>0.000000</CorrInvAmountToDiffAcct>
                <WTLiable>tNO</WTLiable>
                <DeferredTax>tYES</DeferredTax>
                <MeasureUnit>PZA</MeasureUnit>
                <UnitsOfMeasurment>1.000000</UnitsOfMeasurment>
                <LineTotal>1641.650000</LineTotal>
                <TaxPercentagePerRow>16.000000</TaxPercentagePerRow>
                <TaxTotal>262.664000</TaxTotal>
                <ConsumerSalesForecast>tNO</ConsumerSalesForecast>
                <ExciseAmount>0.000000</ExciseAmount>
                <SWW />
                <DistributeExpense>tYES</DistributeExpense>
                <RowTotalFC>72.319000</RowTotalFC>
                <TaxOnly>tNO</TaxOnly>
                <UnitPrice>328.330000</UnitPrice>
                <LineStatus>bost_Close</LineStatus>
                <PackageQuantity>5.000000</PackageQuantity>
                <LineType>dlt_Regular</LineType>
                <ChangeAssemlyBoMWarehouse>N</ChangeAssemlyBoMWarehouse>
                <GrossBuyPrice>0.000000</GrossBuyPrice>
                <GrossProfitTotalBasePrice>0.000000</GrossProfitTotalBasePrice>
                <WithoutInventoryMovement>tNO</WithoutInventoryMovement>
                <DocEntry>6354</DocEntry>
                <ConsiderQuantity>tNO</ConsiderQuantity>
                <PartialRetirement>tNO</PartialRetirement>
                <RetirementAPC>0.000000</RetirementAPC>
                <ThirdParty>tNO</ThirdParty>
                <GrossProfit>0.000000</GrossProfit>
                <GrossProfitFC>0.000000</GrossProfitFC>
                <GrossProfitSC>0.000000</GrossProfitSC>
                <UoMEntry>-1</UoMEntry>
                <InventoryQuantity>5.000000</InventoryQuantity>
                <ChangeInventoryQuantityIndependently>tNO</ChangeInventoryQuantityIndependently>
                <FreeOfChargeBP>tNO</FreeOfChargeBP>
                <GrossPrice>380.862800</GrossPrice>
                <GrossTotal>1904.314000</GrossTotal>
                <GrossTotalFC>83.890000</GrossTotalFC>
                <NCMCode>-1</NCMCode>
                <U_Procesado>0</U_Procesado>
            </row>
        </Document_Lines>
       
    </BO>
</BOM>